edgegap_settings/__init__.py
edgegap_settings/_apm.py
edgegap_settings/_base.py
edgegap_settings/_configuration.py
edgegap_settings/_factory.py
edgegap_settings/_fields.py
edgegap_settings/_logstash.py
edgegap_settings/_meta_data.py
edgegap_settings/_model.py
edgegap_settings-1.8.12.dist-info/LICENSE
edgegap_settings-1.8.12.dist-info/METADATA
edgegap_settings-1.8.12.dist-info/WHEEL
edgegap_settings-1.8.12.dist-info/RECORD
