Metadata-Version: 2.1
Name: edgegap-settings
Version: 1.8.12
Summary: The Edgegap Settings library includes various tools and helpers for interacting with Explicit Settings Models. It is designed for use within the Edgegap organization.
Author: Bastien Roy
Author-email: bastien@edgegap.com
Requires-Python: >=3.10,<4.0
Classifier: Programming Language :: Python :: 3
Classifier: Programming Language :: Python :: 3.10
Classifier: Programming Language :: Python :: 3.11
Classifier: Programming Language :: Python :: 3.12
Requires-Dist: edgegap-consul (>=1.0.0,<2.0.0)
Requires-Dist: edgegap-logging (>=1.0.0,<2.0.0)
Requires-Dist: elastic-apm (>=6.22.0,<7.0.0)
Requires-Dist: pydantic (>=2.7.1,<3.0.0)
Requires-Dist: pydantic-settings (>=2.2.1,<3.0.0)
Requires-Dist: python-dotenv (>=1.0.1,<2.0.0)
Requires-Dist: python-logstash-async (>=3.0.0,<4.0.0)
